evdutyapi/__init__.py
evdutyapi/evduty_api.py
evdutyapi/evduty_api_errors.py
evdutyapi/charging_sessions/__init__.py
evdutyapi/charging_sessions/charging_session.py
evdutyapi/charging_sessions/charging_session_response.py
evdutyapi/max_charging_current/__init__.py
evdutyapi/max_charging_current/max_charging_current_request.py
evdutyapi/stations/__init__.py
evdutyapi/stations/station.py
evdutyapi/stations/station_response.py
evdutyapi/terminals/__init__.py
evdutyapi/terminals/terminal.py
evdutyapi/terminals/terminal_response.py
evduty_api-1.1.0.dist-info/METADATA
evduty_api-1.1.0.dist-info/WHEEL
evduty_api-1.1.0.dist-info/licenses/LICENSE
evduty_api-1.1.0.dist-info/RECORD
