Metadata-Version: 2.4
Name: evduty-api
Version: 1.1.0
Summary: Library to communicate with EVduty REST api
Project-URL: Homepage, https://github.com/happydev-ca/evduty-api
Project-URL: Issues, https://github.com/happydev-ca/evduty-api/issues
Author-email: Francois Perron <fperron@gmail.com>
License-File: LICENSE
Classifier: Development Status :: 5 - Production/Stable
Classifier: License :: OSI Approved :: MIT License
Classifier: Operating System :: OS Independent
Classifier: Programming Language :: Python :: 3
Classifier: Topic :: Home Automation
Requires-Python: >=3.11
Requires-Dist: aiohttp
